ajents/base.py
ajents/pg.py
ajents-0.0.1.dist-info/WHEEL
ajents-0.0.1.dist-info/METADATA
ajents-0.0.1.dist-info/RECORD
